{
  "schema_version": 1,
  "site": {
    "name": "IAP-LACS Forecast",
    "domain": "iaplacs.xyz"
  },
  "published_at": "2026-07-20T11:16:19+08:00",
  "services": {
    "airport": {
      "title": "机场气象服务",
      "subtitle": "Airport weather service",
      "note": "主页作为机场服务入口，当前保留降水、2米气温和10米风场样例产品；后续可替换为机场实况、短临和专用模式产品。",
      "latest_run": "airport_20260709_08",
      "runs": [
        {
          "id": "airport_20260709_08",
          "label": "2026-07-09 08:00 BJT",
          "run_time": "2026-07-09T08:00:00+08:00",
          "published_at": "2026-07-10T01:12:29+08:00",
          "summary": "机场服务样例产品，包含降水、气温和风场。",
          "products": [
            {
              "id": "airport_precip",
              "title": "机场降水预报",
              "category": "机场服务",
              "unit": "mm",
              "color": "#0f68c8",
              "description": "机场周边降水落区和强度样例产品，用于后续接入机场短临保障数据。",
              "metrics": [
                {
                  "label": "产品状态",
                  "value": "样例接入"
                },
                {
                  "label": "图像数量",
                  "value": "2"
                },
                {
                  "label": "服务对象",
                  "value": "机场保障"
                }
              ],
              "frames": [
                {
                  "id": "f024",
                  "lead": 24,
                  "lead_label": "F024",
                  "valid_time": "2026-07-10T08:00:00+08:00",
                  "file": "./data/current/maps/precip_f024.svg",
                  "bytes": 2612
                },
                {
                  "id": "f048",
                  "lead": 48,
                  "lead_label": "F048",
                  "valid_time": "2026-07-11T08:00:00+08:00",
                  "file": "./data/current/maps/precip_f048.svg",
                  "bytes": 2551
                }
              ]
            },
            {
              "id": "airport_temperature",
              "title": "机场 2 米气温",
              "category": "机场服务",
              "unit": "degC",
              "color": "#b73b3b",
              "description": "近地面气温分布样例产品，用于识别机场周边冷暖区和边界层温度变化。",
              "metrics": [
                {
                  "label": "区域最高",
                  "value": "36.2 degC"
                },
                {
                  "label": "区域最低",
                  "value": "17.4 degC"
                },
                {
                  "label": "产品状态",
                  "value": "样例接入"
                }
              ],
              "frames": [
                {
                  "id": "f024",
                  "lead": 24,
                  "lead_label": "F024",
                  "valid_time": "2026-07-10T08:00:00+08:00",
                  "file": "./data/current/maps/temp_f024.svg",
                  "bytes": 1544
                },
                {
                  "id": "f048",
                  "lead": 48,
                  "lead_label": "F048",
                  "valid_time": "2026-07-11T08:00:00+08:00",
                  "file": "./data/current/maps/temp_f048.svg",
                  "bytes": 1544
                }
              ]
            },
            {
              "id": "airport_wind",
              "title": "机场 10 米风场",
              "category": "机场服务",
              "unit": "m/s",
              "color": "#2c5f9e",
              "description": "近地面风速和风向样例产品，用于展示机场风场保障产品入口。",
              "metrics": [
                {
                  "label": "最大风速",
                  "value": "15.8 m/s"
                },
                {
                  "label": "主导风向",
                  "value": "SE"
                },
                {
                  "label": "产品状态",
                  "value": "样例接入"
                }
              ],
              "frames": [
                {
                  "id": "f024",
                  "lead": 24,
                  "lead_label": "F024",
                  "valid_time": "2026-07-10T08:00:00+08:00",
                  "file": "./data/current/maps/wind_f024.svg",
                  "bytes": 2150
                },
                {
                  "id": "f048",
                  "lead": 48,
                  "lead_label": "F048",
                  "valid_time": "2026-07-11T08:00:00+08:00",
                  "file": "./data/current/maps/wind_f048.svg",
                  "bytes": 2141
                }
              ]
            }
          ]
        }
      ]
    },
    "main": {
      "title": "机场气象服务",
      "subtitle": "Airport weather service",
      "note": "兼容旧入口：主页已调整为机场服务。",
      "latest_run": "airport_20260709_08",
      "runs": [
        {
          "id": "airport_20260709_08",
          "label": "2026-07-09 08:00 BJT",
          "run_time": "2026-07-09T08:00:00+08:00",
          "published_at": "2026-07-10T01:12:29+08:00",
          "summary": "机场服务样例产品，包含降水、气温和风场。",
          "products": [
            {
              "id": "airport_precip",
              "title": "机场降水预报",
              "category": "机场服务",
              "unit": "mm",
              "color": "#0f68c8",
              "description": "机场周边降水落区和强度样例产品，用于后续接入机场短临保障数据。",
              "metrics": [
                {
                  "label": "产品状态",
                  "value": "样例接入"
                },
                {
                  "label": "图像数量",
                  "value": "2"
                },
                {
                  "label": "服务对象",
                  "value": "机场保障"
                }
              ],
              "frames": [
                {
                  "id": "f024",
                  "lead": 24,
                  "lead_label": "F024",
                  "valid_time": "2026-07-10T08:00:00+08:00",
                  "file": "./data/current/maps/precip_f024.svg",
                  "bytes": 2612
                },
                {
                  "id": "f048",
                  "lead": 48,
                  "lead_label": "F048",
                  "valid_time": "2026-07-11T08:00:00+08:00",
                  "file": "./data/current/maps/precip_f048.svg",
                  "bytes": 2551
                }
              ]
            },
            {
              "id": "airport_temperature",
              "title": "机场 2 米气温",
              "category": "机场服务",
              "unit": "degC",
              "color": "#b73b3b",
              "description": "近地面气温分布样例产品，用于识别机场周边冷暖区和边界层温度变化。",
              "metrics": [
                {
                  "label": "区域最高",
                  "value": "36.2 degC"
                },
                {
                  "label": "区域最低",
                  "value": "17.4 degC"
                },
                {
                  "label": "产品状态",
                  "value": "样例接入"
                }
              ],
              "frames": [
                {
                  "id": "f024",
                  "lead": 24,
                  "lead_label": "F024",
                  "valid_time": "2026-07-10T08:00:00+08:00",
                  "file": "./data/current/maps/temp_f024.svg",
                  "bytes": 1544
                },
                {
                  "id": "f048",
                  "lead": 48,
                  "lead_label": "F048",
                  "valid_time": "2026-07-11T08:00:00+08:00",
                  "file": "./data/current/maps/temp_f048.svg",
                  "bytes": 1544
                }
              ]
            },
            {
              "id": "airport_wind",
              "title": "机场 10 米风场",
              "category": "机场服务",
              "unit": "m/s",
              "color": "#2c5f9e",
              "description": "近地面风速和风向样例产品，用于展示机场风场保障产品入口。",
              "metrics": [
                {
                  "label": "最大风速",
                  "value": "15.8 m/s"
                },
                {
                  "label": "主导风向",
                  "value": "SE"
                },
                {
                  "label": "产品状态",
                  "value": "样例接入"
                }
              ],
              "frames": [
                {
                  "id": "f024",
                  "lead": 24,
                  "lead_label": "F024",
                  "valid_time": "2026-07-10T08:00:00+08:00",
                  "file": "./data/current/maps/wind_f024.svg",
                  "bytes": 2150
                },
                {
                  "id": "f048",
                  "lead": 48,
                  "lead_label": "F048",
                  "valid_time": "2026-07-11T08:00:00+08:00",
                  "file": "./data/current/maps/wind_f048.svg",
                  "bytes": 2141
                }
              ]
            }
          ]
        }
      ]
    },
    "ningxia": {
      "title": "宁夏预报",
      "subtitle": "Ningxia forecast",
      "note": "宁夏页面集中展示 WORK_nx 发布的宁夏区域预报图。新起报时次推送到仓库后，会自动出现在顶部起报时间选择区。",
      "latest_run": "20260719_18",
      "runs": [
        {
          "id": "20260719_18",
          "label": "2026-07-20 02:00 BJT",
          "run_time": "2026-07-20T02:00:00+08:00",
          "published_at": "2026-07-20T10:59:01+08:00",
          "summary": "宁夏区域预报图集，共 1 张图",
          "products": [
            {
              "id": "ningxia_precip_series",
              "title": "降水预报图集",
              "category": "宁夏预报",
              "unit": "mm",
              "color": "#0f68c8",
              "description": "WORK_nx 目录下的降水预报图集，按起报时次手动归档。",
              "metrics": [
                {
                  "label": "起报时次",
                  "value": "20260719 18 UTC"
                },
                {
                  "label": "生成时间",
                  "value": "2026-07-20 10:59 BJT"
                },
                {
                  "label": "图像数量",
                  "value": "1"
                }
              ],
              "frames": [
                {
                  "id": "precip_hourly_wrf_ningxia_t13_t48_initutc_2026_07_19_18_00_combined_overview_6x6_grid",
                  "lead": 48,
                  "lead_label": "T13-T48",
                  "file": "https://iaplacs-forecast-images-hk.oss-cn-hongkong.aliyuncs.com/iaplacs/data/current/maps/worknx_summary_20260719_18/Precip_hourly_WRF_Ningxia_T13_T48_InitUTC_2026-07-19_18_00_combined_overview_6x6_grid.webp",
                  "bytes": 1927548,
                  "preview_file": "https://iaplacs-forecast-images-hk.oss-cn-hongkong.aliyuncs.com/iaplacs/data/current/maps/worknx_summary_20260719_18/Precip_hourly_WRF_Ningxia_T13_T48_InitUTC_2026-07-19_18_00_combined_overview_6x6_grid.preview.webp",
                  "preview_bytes": 416308,
                  "full_file": "https://iaplacs-forecast-images-hk.oss-cn-hongkong.aliyuncs.com/iaplacs/data/current/maps/worknx_summary_20260719_18/Precip_hourly_WRF_Ningxia_T13_T48_InitUTC_2026-07-19_18_00_combined_overview_6x6_grid.png",
                  "full_bytes": 1420686,
                  "valid_time": "2026-07-22T02:00:00+08:00"
                }
              ]
            }
          ]
        },
        {
          "id": "20260719_12",
          "label": "2026-07-19 20:00 BJT",
          "run_time": "2026-07-19T20:00:00+08:00",
          "published_at": "2026-07-20T05:03:37+08:00",
          "summary": "宁夏区域预报图集，共 1 张图",
          "products": [
            {
              "id": "ningxia_precip_series",
              "title": "降水预报图集",
              "category": "宁夏预报",
              "unit": "mm",
              "color": "#0f68c8",
              "description": "WORK_nx 目录下的降水预报图集，按起报时次手动归档。",
              "metrics": [
                {
                  "label": "起报时次",
                  "value": "20260719 12 UTC"
                },
                {
                  "label": "生成时间",
                  "value": "2026-07-20 05:03 BJT"
                },
                {
                  "label": "图像数量",
                  "value": "1"
                }
              ],
              "frames": [
                {
                  "id": "precip_hourly_wrf_ningxia_t13_t48_initutc_2026_07_19_12_00_combined_overview_6x6_grid",
                  "lead": 48,
                  "lead_label": "T13-T48",
                  "file": "https://iaplacs-forecast-images-hk.oss-cn-hongkong.aliyuncs.com/iaplacs/data/current/maps/worknx_summary_20260719_12/Precip_hourly_WRF_Ningxia_T13_T48_InitUTC_2026-07-19_12_00_combined_overview_6x6_grid.webp",
                  "bytes": 1844971,
                  "preview_file": "https://iaplacs-forecast-images-hk.oss-cn-hongkong.aliyuncs.com/iaplacs/data/current/maps/worknx_summary_20260719_12/Precip_hourly_WRF_Ningxia_T13_T48_InitUTC_2026-07-19_12_00_combined_overview_6x6_grid.preview.webp",
                  "preview_bytes": 392404,
                  "full_file": "https://iaplacs-forecast-images-hk.oss-cn-hongkong.aliyuncs.com/iaplacs/data/current/maps/worknx_summary_20260719_12/Precip_hourly_WRF_Ningxia_T13_T48_InitUTC_2026-07-19_12_00_combined_overview_6x6_grid.png",
                  "full_bytes": 1373793,
                  "valid_time": "2026-07-21T20:00:00+08:00"
                }
              ]
            }
          ]
        },
        {
          "id": "20260719_06",
          "label": "2026-07-19 14:00 BJT",
          "run_time": "2026-07-19T14:00:00+08:00",
          "published_at": "2026-07-19T23:06:46+08:00",
          "summary": "宁夏区域预报图集，共 1 张图",
          "products": [
            {
              "id": "ningxia_precip_series",
              "title": "降水预报图集",
              "category": "宁夏预报",
              "unit": "mm",
              "color": "#0f68c8",
              "description": "WORK_nx 目录下的降水预报图集，按起报时次手动归档。",
              "metrics": [
                {
                  "label": "起报时次",
                  "value": "20260719 06 UTC"
                },
                {
                  "label": "生成时间",
                  "value": "2026-07-19 23:06 BJT"
                },
                {
                  "label": "图像数量",
                  "value": "1"
                }
              ],
              "frames": [
                {
                  "id": "precip_hourly_wrf_ningxia_t13_t48_initutc_2026_07_19_06_00_combined_overview_6x6_grid",
                  "lead": 48,
                  "lead_label": "T13-T48",
                  "file": "https://iaplacs-forecast-images-hk.oss-cn-hongkong.aliyuncs.com/iaplacs/data/current/maps/worknx_summary_20260719_06/Precip_hourly_WRF_Ningxia_T13_T48_InitUTC_2026-07-19_06_00_combined_overview_6x6_grid.webp",
                  "bytes": 1788195,
                  "preview_file": "https://iaplacs-forecast-images-hk.oss-cn-hongkong.aliyuncs.com/iaplacs/data/current/maps/worknx_summary_20260719_06/Precip_hourly_WRF_Ningxia_T13_T48_InitUTC_2026-07-19_06_00_combined_overview_6x6_grid.preview.webp",
                  "preview_bytes": 377643,
                  "full_file": "https://iaplacs-forecast-images-hk.oss-cn-hongkong.aliyuncs.com/iaplacs/data/current/maps/worknx_summary_20260719_06/Precip_hourly_WRF_Ningxia_T13_T48_InitUTC_2026-07-19_06_00_combined_overview_6x6_grid.png",
                  "full_bytes": 1343922,
                  "valid_time": "2026-07-21T14:00:00+08:00"
                }
              ]
            }
          ]
        },
        {
          "id": "20260719_00",
          "label": "2026-07-19 08:00 BJT",
          "run_time": "2026-07-19T08:00:00+08:00",
          "published_at": "2026-07-19T17:06:11+08:00",
          "summary": "宁夏区域预报图集，共 1 张图",
          "products": [
            {
              "id": "ningxia_precip_series",
              "title": "降水预报图集",
              "category": "宁夏预报",
              "unit": "mm",
              "color": "#0f68c8",
              "description": "WORK_nx 目录下的降水预报图集，按起报时次手动归档。",
              "metrics": [
                {
                  "label": "起报时次",
                  "value": "20260719 00 UTC"
                },
                {
                  "label": "生成时间",
                  "value": "2026-07-19 17:06 BJT"
                },
                {
                  "label": "图像数量",
                  "value": "1"
                }
              ],
              "frames": [
                {
                  "id": "precip_hourly_wrf_ningxia_t13_t48_initutc_2026_07_19_00_00_combined_overview_6x6_grid",
                  "lead": 48,
                  "lead_label": "T13-T48",
                  "file": "https://iaplacs-forecast-images-hk.oss-cn-hongkong.aliyuncs.com/iaplacs/data/current/maps/worknx_summary_20260719_00/Precip_hourly_WRF_Ningxia_T13_T48_InitUTC_2026-07-19_00_00_combined_overview_6x6_grid.webp",
                  "bytes": 1715299,
                  "preview_file": "https://iaplacs-forecast-images-hk.oss-cn-hongkong.aliyuncs.com/iaplacs/data/current/maps/worknx_summary_20260719_00/Precip_hourly_WRF_Ningxia_T13_T48_InitUTC_2026-07-19_00_00_combined_overview_6x6_grid.preview.webp",
                  "preview_bytes": 349317,
                  "full_file": "https://iaplacs-forecast-images-hk.oss-cn-hongkong.aliyuncs.com/iaplacs/data/current/maps/worknx_summary_20260719_00/Precip_hourly_WRF_Ningxia_T13_T48_InitUTC_2026-07-19_00_00_combined_overview_6x6_grid.png",
                  "full_bytes": 1308489,
                  "valid_time": "2026-07-21T08:00:00+08:00"
                }
              ]
            }
          ]
        },
        {
          "id": "20260718_18",
          "label": "2026-07-19 02:00 BJT",
          "run_time": "2026-07-19T02:00:00+08:00",
          "published_at": "2026-07-19T11:00:48+08:00",
          "summary": "宁夏区域预报图集，共 1 张图",
          "products": [
            {
              "id": "ningxia_precip_series",
              "title": "降水预报图集",
              "category": "宁夏预报",
              "unit": "mm",
              "color": "#0f68c8",
              "description": "WORK_nx 目录下的降水预报图集，按起报时次手动归档。",
              "metrics": [
                {
                  "label": "起报时次",
                  "value": "20260718 18 UTC"
                },
                {
                  "label": "生成时间",
                  "value": "2026-07-19 11:00 BJT"
                },
                {
                  "label": "图像数量",
                  "value": "1"
                }
              ],
              "frames": [
                {
                  "id": "precip_hourly_wrf_ningxia_t13_t48_initutc_2026_07_18_18_00_combined_overview_6x6_grid",
                  "lead": 48,
                  "lead_label": "T13-T48",
                  "file": "https://iaplacs-forecast-images-hk.oss-cn-hongkong.aliyuncs.com/iaplacs/data/current/maps/worknx_summary_20260718_18/Precip_hourly_WRF_Ningxia_T13_T48_InitUTC_2026-07-18_18_00_combined_overview_6x6_grid.webp",
                  "bytes": 1753213,
                  "preview_file": "https://iaplacs-forecast-images-hk.oss-cn-hongkong.aliyuncs.com/iaplacs/data/current/maps/worknx_summary_20260718_18/Precip_hourly_WRF_Ningxia_T13_T48_InitUTC_2026-07-18_18_00_combined_overview_6x6_grid.preview.webp",
                  "preview_bytes": 360778,
                  "full_file": "https://iaplacs-forecast-images-hk.oss-cn-hongkong.aliyuncs.com/iaplacs/data/current/maps/worknx_summary_20260718_18/Precip_hourly_WRF_Ningxia_T13_T48_InitUTC_2026-07-18_18_00_combined_overview_6x6_grid.png",
                  "full_bytes": 1326321,
                  "valid_time": "2026-07-21T02:00:00+08:00"
                }
              ]
            }
          ]
        }
      ]
    },
    "shangrao": {
      "title": "上饶专项天气服务",
      "subtitle": "Shangrao service",
      "note": "上饶服务页按起报时次展示服务器定时发布的 WRF 逐小时降水拼图，页面会在新的清单提交后自动读取最新时次。",
      "latest_run": "20260719_20",
      "runs": [
        {
          "id": "20260719_20",
          "label": "2026-07-19 20:00 BJT",
          "run_time": "2026-07-19T20:00:00+08:00",
          "published_at": "2026-07-20T05:16:28+08:00",
          "summary": "WRF 逐小时降水拼图，共 4 张图",
          "products": [
            {
              "id": "wrf_rain_montage",
              "title": "上饶 WRF 逐小时降水拼图",
              "category": "上饶预报",
              "unit": "mm",
              "color": "#0f68c8",
              "description": "上饶服务起报时次 20260719_20，包含总览图和分段细节图。",
              "metrics": [
                {
                  "label": "起报时次",
                  "value": "20260719 20 BJT"
                },
                {
                  "label": "图像数量",
                  "value": "4"
                },
                {
                  "label": "产品状态",
                  "value": "服务器发布"
                }
              ],
              "frames": [
                {
                  "id": "overview",
                  "lead": 48,
                  "lead_label": "总览",
                  "valid_label": "",
                  "file": "https://iaplacs-forecast-images-hk.oss-cn-hongkong.aliyuncs.com/iaplacs/data/current/maps/wrf_montage_20260719_20/20260719_20_combined_overview_6x6_grid.webp",
                  "bytes": 3217461,
                  "preview_file": "https://iaplacs-forecast-images-hk.oss-cn-hongkong.aliyuncs.com/iaplacs/data/current/maps/wrf_montage_20260719_20/20260719_20_combined_overview_6x6_grid.preview.webp",
                  "preview_bytes": 729791,
                  "full_file": "https://iaplacs-forecast-images-hk.oss-cn-hongkong.aliyuncs.com/iaplacs/data/current/maps/wrf_montage_20260719_20/20260719_20_combined_overview_6x6_grid.png",
                  "full_bytes": 1782716
                },
                {
                  "id": "detail_p01",
                  "lead": 24,
                  "lead_label": "07-20 08-20",
                  "valid_label": "",
                  "file": "https://iaplacs-forecast-images-hk.oss-cn-hongkong.aliyuncs.com/iaplacs/data/current/maps/wrf_montage_20260719_20/20260719_20_combined_detail_p01_4x3_grid.webp",
                  "bytes": 1178903,
                  "preview_file": "https://iaplacs-forecast-images-hk.oss-cn-hongkong.aliyuncs.com/iaplacs/data/current/maps/wrf_montage_20260719_20/20260719_20_combined_detail_p01_4x3_grid.preview.webp",
                  "preview_bytes": 366476,
                  "full_file": "https://iaplacs-forecast-images-hk.oss-cn-hongkong.aliyuncs.com/iaplacs/data/current/maps/wrf_montage_20260719_20/20260719_20_combined_detail_p01_4x3_grid.png",
                  "full_bytes": 741062
                },
                {
                  "id": "detail_p02",
                  "lead": 36,
                  "lead_label": "07-20 20-08",
                  "valid_label": "",
                  "file": "https://iaplacs-forecast-images-hk.oss-cn-hongkong.aliyuncs.com/iaplacs/data/current/maps/wrf_montage_20260719_20/20260719_20_combined_detail_p02_4x3_grid.webp",
                  "bytes": 1053415,
                  "preview_file": "https://iaplacs-forecast-images-hk.oss-cn-hongkong.aliyuncs.com/iaplacs/data/current/maps/wrf_montage_20260719_20/20260719_20_combined_detail_p02_4x3_grid.preview.webp",
                  "preview_bytes": 325289,
                  "full_file": "https://iaplacs-forecast-images-hk.oss-cn-hongkong.aliyuncs.com/iaplacs/data/current/maps/wrf_montage_20260719_20/20260719_20_combined_detail_p02_4x3_grid.png",
                  "full_bytes": 705761
                },
                {
                  "id": "detail_p03",
                  "lead": 48,
                  "lead_label": "07-21 08-20",
                  "valid_label": "",
                  "file": "https://iaplacs-forecast-images-hk.oss-cn-hongkong.aliyuncs.com/iaplacs/data/current/maps/wrf_montage_20260719_20/20260719_20_combined_detail_p03_4x3_grid.webp",
                  "bytes": 1052493,
                  "preview_file": "https://iaplacs-forecast-images-hk.oss-cn-hongkong.aliyuncs.com/iaplacs/data/current/maps/wrf_montage_20260719_20/20260719_20_combined_detail_p03_4x3_grid.preview.webp",
                  "preview_bytes": 316801,
                  "full_file": "https://iaplacs-forecast-images-hk.oss-cn-hongkong.aliyuncs.com/iaplacs/data/current/maps/wrf_montage_20260719_20/20260719_20_combined_detail_p03_4x3_grid.png",
                  "full_bytes": 709975
                }
              ]
            }
          ]
        },
        {
          "id": "20260719_14",
          "label": "2026-07-19 14:00 BJT",
          "run_time": "2026-07-19T14:00:00+08:00",
          "published_at": "2026-07-20T05:16:20+08:00",
          "summary": "WRF 逐小时降水拼图，共 4 张图",
          "products": [
            {
              "id": "wrf_rain_montage",
              "title": "上饶 WRF 逐小时降水拼图",
              "category": "上饶预报",
              "unit": "mm",
              "color": "#0f68c8",
              "description": "上饶服务起报时次 20260719_14，包含总览图和分段细节图。",
              "metrics": [
                {
                  "label": "起报时次",
                  "value": "20260719 14 BJT"
                },
                {
                  "label": "图像数量",
                  "value": "4"
                },
                {
                  "label": "产品状态",
                  "value": "服务器发布"
                }
              ],
              "frames": [
                {
                  "id": "overview",
                  "lead": 48,
                  "lead_label": "总览",
                  "valid_label": "",
                  "file": "https://iaplacs-forecast-images-hk.oss-cn-hongkong.aliyuncs.com/iaplacs/data/current/maps/wrf_montage_20260719_14/20260719_14_combined_overview_6x6_grid.webp",
                  "bytes": 3490956,
                  "preview_file": "https://iaplacs-forecast-images-hk.oss-cn-hongkong.aliyuncs.com/iaplacs/data/current/maps/wrf_montage_20260719_14/20260719_14_combined_overview_6x6_grid.preview.webp",
                  "preview_bytes": 785908,
                  "full_file": "https://iaplacs-forecast-images-hk.oss-cn-hongkong.aliyuncs.com/iaplacs/data/current/maps/wrf_montage_20260719_14/20260719_14_combined_overview_6x6_grid.png",
                  "full_bytes": 1847155
                },
                {
                  "id": "detail_p01",
                  "lead": 24,
                  "lead_label": "07-20 02-14",
                  "valid_label": "",
                  "file": "https://iaplacs-forecast-images-hk.oss-cn-hongkong.aliyuncs.com/iaplacs/data/current/maps/wrf_montage_20260719_14/20260719_14_combined_detail_p01_4x3_grid.webp",
                  "bytes": 1307192,
                  "preview_file": "https://iaplacs-forecast-images-hk.oss-cn-hongkong.aliyuncs.com/iaplacs/data/current/maps/wrf_montage_20260719_14/20260719_14_combined_detail_p01_4x3_grid.preview.webp",
                  "preview_bytes": 403810,
                  "full_file": "https://iaplacs-forecast-images-hk.oss-cn-hongkong.aliyuncs.com/iaplacs/data/current/maps/wrf_montage_20260719_14/20260719_14_combined_detail_p01_4x3_grid.png",
                  "full_bytes": 772197
                },
                {
                  "id": "detail_p02",
                  "lead": 36,
                  "lead_label": "07-20 14-02",
                  "valid_label": "",
                  "file": "https://iaplacs-forecast-images-hk.oss-cn-hongkong.aliyuncs.com/iaplacs/data/current/maps/wrf_montage_20260719_14/20260719_14_combined_detail_p02_4x3_grid.webp",
                  "bytes": 1147897,
                  "preview_file": "https://iaplacs-forecast-images-hk.oss-cn-hongkong.aliyuncs.com/iaplacs/data/current/maps/wrf_montage_20260719_14/20260719_14_combined_detail_p02_4x3_grid.preview.webp",
                  "preview_bytes": 350742,
                  "full_file": "https://iaplacs-forecast-images-hk.oss-cn-hongkong.aliyuncs.com/iaplacs/data/current/maps/wrf_montage_20260719_14/20260719_14_combined_detail_p02_4x3_grid.png",
                  "full_bytes": 741655
                },
                {
                  "id": "detail_p03",
                  "lead": 48,
                  "lead_label": "07-21 02-14",
                  "valid_label": "",
                  "file": "https://iaplacs-forecast-images-hk.oss-cn-hongkong.aliyuncs.com/iaplacs/data/current/maps/wrf_montage_20260719_14/20260719_14_combined_detail_p03_4x3_grid.webp",
                  "bytes": 1170548,
                  "preview_file": "https://iaplacs-forecast-images-hk.oss-cn-hongkong.aliyuncs.com/iaplacs/data/current/maps/wrf_montage_20260719_14/20260719_14_combined_detail_p03_4x3_grid.preview.webp",
                  "preview_bytes": 360517,
                  "full_file": "https://iaplacs-forecast-images-hk.oss-cn-hongkong.aliyuncs.com/iaplacs/data/current/maps/wrf_montage_20260719_14/20260719_14_combined_detail_p03_4x3_grid.png",
                  "full_bytes": 717632
                }
              ]
            }
          ]
        },
        {
          "id": "20260719_08",
          "label": "2026-07-19 08:00 BJT",
          "run_time": "2026-07-19T08:00:00+08:00",
          "published_at": "2026-07-20T11:16:19+08:00",
          "summary": "WRF 逐小时降水拼图，共 4 张图",
          "products": [
            {
              "id": "wrf_rain_montage",
              "title": "上饶 WRF 逐小时降水拼图",
              "category": "上饶预报",
              "unit": "mm",
              "color": "#0f68c8",
              "description": "上饶服务起报时次 20260719_08，包含总览图和分段细节图。",
              "metrics": [
                {
                  "label": "起报时次",
                  "value": "20260719 08 BJT"
                },
                {
                  "label": "图像数量",
                  "value": "4"
                },
                {
                  "label": "产品状态",
                  "value": "服务器发布"
                }
              ],
              "frames": [
                {
                  "id": "overview",
                  "lead": 48,
                  "lead_label": "总览",
                  "valid_label": "",
                  "file": "https://iaplacs-forecast-images-hk.oss-cn-hongkong.aliyuncs.com/iaplacs/data/current/maps/wrf_montage_20260719_08/20260719_08_combined_overview_6x6_grid.webp",
                  "bytes": 3509253,
                  "preview_file": "https://iaplacs-forecast-images-hk.oss-cn-hongkong.aliyuncs.com/iaplacs/data/current/maps/wrf_montage_20260719_08/20260719_08_combined_overview_6x6_grid.preview.webp",
                  "preview_bytes": 780241,
                  "full_file": "https://iaplacs-forecast-images-hk.oss-cn-hongkong.aliyuncs.com/iaplacs/data/current/maps/wrf_montage_20260719_08/20260719_08_combined_overview_6x6_grid.png",
                  "full_bytes": 1863601
                },
                {
                  "id": "detail_p01",
                  "lead": 24,
                  "lead_label": "07-19 20-08",
                  "valid_label": "",
                  "file": "https://iaplacs-forecast-images-hk.oss-cn-hongkong.aliyuncs.com/iaplacs/data/current/maps/wrf_montage_20260719_08/20260719_08_combined_detail_p01_4x3_grid.webp",
                  "bytes": 1396601,
                  "preview_file": "https://iaplacs-forecast-images-hk.oss-cn-hongkong.aliyuncs.com/iaplacs/data/current/maps/wrf_montage_20260719_08/20260719_08_combined_detail_p01_4x3_grid.preview.webp",
                  "preview_bytes": 424592,
                  "full_file": "https://iaplacs-forecast-images-hk.oss-cn-hongkong.aliyuncs.com/iaplacs/data/current/maps/wrf_montage_20260719_08/20260719_08_combined_detail_p01_4x3_grid.png",
                  "full_bytes": 799369
                },
                {
                  "id": "detail_p02",
                  "lead": 36,
                  "lead_label": "07-20 08-20",
                  "valid_label": "",
                  "file": "https://iaplacs-forecast-images-hk.oss-cn-hongkong.aliyuncs.com/iaplacs/data/current/maps/wrf_montage_20260719_08/20260719_08_combined_detail_p02_4x3_grid.webp",
                  "bytes": 1154618,
                  "preview_file": "https://iaplacs-forecast-images-hk.oss-cn-hongkong.aliyuncs.com/iaplacs/data/current/maps/wrf_montage_20260719_08/20260719_08_combined_detail_p02_4x3_grid.preview.webp",
                  "preview_bytes": 349232,
                  "full_file": "https://iaplacs-forecast-images-hk.oss-cn-hongkong.aliyuncs.com/iaplacs/data/current/maps/wrf_montage_20260719_08/20260719_08_combined_detail_p02_4x3_grid.png",
                  "full_bytes": 734726
                },
                {
                  "id": "detail_p03",
                  "lead": 48,
                  "lead_label": "07-20 20-08",
                  "valid_label": "",
                  "file": "https://iaplacs-forecast-images-hk.oss-cn-hongkong.aliyuncs.com/iaplacs/data/current/maps/wrf_montage_20260719_08/20260719_08_combined_detail_p03_4x3_grid.webp",
                  "bytes": 1102797,
                  "preview_file": "https://iaplacs-forecast-images-hk.oss-cn-hongkong.aliyuncs.com/iaplacs/data/current/maps/wrf_montage_20260719_08/20260719_08_combined_detail_p03_4x3_grid.preview.webp",
                  "preview_bytes": 337063,
                  "full_file": "https://iaplacs-forecast-images-hk.oss-cn-hongkong.aliyuncs.com/iaplacs/data/current/maps/wrf_montage_20260719_08/20260719_08_combined_detail_p03_4x3_grid.png",
                  "full_bytes": 706160
                }
              ]
            }
          ]
        },
        {
          "id": "20260719_02",
          "label": "2026-07-19 02:00 BJT",
          "run_time": "2026-07-19T02:00:00+08:00",
          "published_at": "2026-07-20T11:16:11+08:00",
          "summary": "WRF 逐小时降水拼图，共 4 张图",
          "products": [
            {
              "id": "wrf_rain_montage",
              "title": "上饶 WRF 逐小时降水拼图",
              "category": "上饶预报",
              "unit": "mm",
              "color": "#0f68c8",
              "description": "上饶服务起报时次 20260719_02，包含总览图和分段细节图。",
              "metrics": [
                {
                  "label": "起报时次",
                  "value": "20260719 02 BJT"
                },
                {
                  "label": "图像数量",
                  "value": "4"
                },
                {
                  "label": "产品状态",
                  "value": "服务器发布"
                }
              ],
              "frames": [
                {
                  "id": "overview",
                  "lead": 48,
                  "lead_label": "总览",
                  "valid_label": "",
                  "file": "https://iaplacs-forecast-images-hk.oss-cn-hongkong.aliyuncs.com/iaplacs/data/current/maps/wrf_montage_20260719_02/20260719_02_combined_overview_6x6_grid.webp",
                  "bytes": 3391992,
                  "preview_file": "https://iaplacs-forecast-images-hk.oss-cn-hongkong.aliyuncs.com/iaplacs/data/current/maps/wrf_montage_20260719_02/20260719_02_combined_overview_6x6_grid.preview.webp",
                  "preview_bytes": 753829,
                  "full_file": "https://iaplacs-forecast-images-hk.oss-cn-hongkong.aliyuncs.com/iaplacs/data/current/maps/wrf_montage_20260719_02/20260719_02_combined_overview_6x6_grid.png",
                  "full_bytes": 1819215
                },
                {
                  "id": "detail_p01",
                  "lead": 24,
                  "lead_label": "07-19 14-02",
                  "valid_label": "",
                  "file": "https://iaplacs-forecast-images-hk.oss-cn-hongkong.aliyuncs.com/iaplacs/data/current/maps/wrf_montage_20260719_02/20260719_02_combined_detail_p01_4x3_grid.webp",
                  "bytes": 1289022,
                  "preview_file": "https://iaplacs-forecast-images-hk.oss-cn-hongkong.aliyuncs.com/iaplacs/data/current/maps/wrf_montage_20260719_02/20260719_02_combined_detail_p01_4x3_grid.preview.webp",
                  "preview_bytes": 387872,
                  "full_file": "https://iaplacs-forecast-images-hk.oss-cn-hongkong.aliyuncs.com/iaplacs/data/current/maps/wrf_montage_20260719_02/20260719_02_combined_detail_p01_4x3_grid.png",
                  "full_bytes": 777418
                },
                {
                  "id": "detail_p02",
                  "lead": 36,
                  "lead_label": "07-20 02-14",
                  "valid_label": "",
                  "file": "https://iaplacs-forecast-images-hk.oss-cn-hongkong.aliyuncs.com/iaplacs/data/current/maps/wrf_montage_20260719_02/20260719_02_combined_detail_p02_4x3_grid.webp",
                  "bytes": 1091818,
                  "preview_file": "https://iaplacs-forecast-images-hk.oss-cn-hongkong.aliyuncs.com/iaplacs/data/current/maps/wrf_montage_20260719_02/20260719_02_combined_detail_p02_4x3_grid.preview.webp",
                  "preview_bytes": 332958,
                  "full_file": "https://iaplacs-forecast-images-hk.oss-cn-hongkong.aliyuncs.com/iaplacs/data/current/maps/wrf_montage_20260719_02/20260719_02_combined_detail_p02_4x3_grid.png",
                  "full_bytes": 703716
                },
                {
                  "id": "detail_p03",
                  "lead": 48,
                  "lead_label": "07-20 14-02",
                  "valid_label": "",
                  "file": "https://iaplacs-forecast-images-hk.oss-cn-hongkong.aliyuncs.com/iaplacs/data/current/maps/wrf_montage_20260719_02/20260719_02_combined_detail_p03_4x3_grid.webp",
                  "bytes": 1133525,
                  "preview_file": "https://iaplacs-forecast-images-hk.oss-cn-hongkong.aliyuncs.com/iaplacs/data/current/maps/wrf_montage_20260719_02/20260719_02_combined_detail_p03_4x3_grid.preview.webp",
                  "preview_bytes": 340089,
                  "full_file": "https://iaplacs-forecast-images-hk.oss-cn-hongkong.aliyuncs.com/iaplacs/data/current/maps/wrf_montage_20260719_02/20260719_02_combined_detail_p03_4x3_grid.png",
                  "full_bytes": 722736
                }
              ]
            }
          ]
        },
        {
          "id": "20260718_20",
          "label": "2026-07-18 20:00 BJT",
          "run_time": "2026-07-18T20:00:00+08:00",
          "published_at": "2026-07-20T11:16:03+08:00",
          "summary": "WRF 逐小时降水拼图，共 4 张图",
          "products": [
            {
              "id": "wrf_rain_montage",
              "title": "上饶 WRF 逐小时降水拼图",
              "category": "上饶预报",
              "unit": "mm",
              "color": "#0f68c8",
              "description": "上饶服务起报时次 20260718_20，包含总览图和分段细节图。",
              "metrics": [
                {
                  "label": "起报时次",
                  "value": "20260718 20 BJT"
                },
                {
                  "label": "图像数量",
                  "value": "4"
                },
                {
                  "label": "产品状态",
                  "value": "服务器发布"
                }
              ],
              "frames": [
                {
                  "id": "overview",
                  "lead": 48,
                  "lead_label": "总览",
                  "valid_label": "",
                  "file": "https://iaplacs-forecast-images-hk.oss-cn-hongkong.aliyuncs.com/iaplacs/data/current/maps/wrf_montage_20260718_20/20260718_20_combined_overview_6x6_grid.webp",
                  "bytes": 3281448,
                  "preview_file": "https://iaplacs-forecast-images-hk.oss-cn-hongkong.aliyuncs.com/iaplacs/data/current/maps/wrf_montage_20260718_20/20260718_20_combined_overview_6x6_grid.preview.webp",
                  "preview_bytes": 728667,
                  "full_file": "https://iaplacs-forecast-images-hk.oss-cn-hongkong.aliyuncs.com/iaplacs/data/current/maps/wrf_montage_20260718_20/20260718_20_combined_overview_6x6_grid.png",
                  "full_bytes": 1815691
                },
                {
                  "id": "detail_p01",
                  "lead": 24,
                  "lead_label": "07-19 08-20",
                  "valid_label": "",
                  "file": "https://iaplacs-forecast-images-hk.oss-cn-hongkong.aliyuncs.com/iaplacs/data/current/maps/wrf_montage_20260718_20/20260718_20_combined_detail_p01_4x3_grid.webp",
                  "bytes": 1138636,
                  "preview_file": "https://iaplacs-forecast-images-hk.oss-cn-hongkong.aliyuncs.com/iaplacs/data/current/maps/wrf_montage_20260718_20/20260718_20_combined_detail_p01_4x3_grid.preview.webp",
                  "preview_bytes": 333375,
                  "full_file": "https://iaplacs-forecast-images-hk.oss-cn-hongkong.aliyuncs.com/iaplacs/data/current/maps/wrf_montage_20260718_20/20260718_20_combined_detail_p01_4x3_grid.png",
                  "full_bytes": 733324
                },
                {
                  "id": "detail_p02",
                  "lead": 36,
                  "lead_label": "07-19 20-08",
                  "valid_label": "",
                  "file": "https://iaplacs-forecast-images-hk.oss-cn-hongkong.aliyuncs.com/iaplacs/data/current/maps/wrf_montage_20260718_20/20260718_20_combined_detail_p02_4x3_grid.webp",
                  "bytes": 1162674,
                  "preview_file": "https://iaplacs-forecast-images-hk.oss-cn-hongkong.aliyuncs.com/iaplacs/data/current/maps/wrf_montage_20260718_20/20260718_20_combined_detail_p02_4x3_grid.preview.webp",
                  "preview_bytes": 354214,
                  "full_file": "https://iaplacs-forecast-images-hk.oss-cn-hongkong.aliyuncs.com/iaplacs/data/current/maps/wrf_montage_20260718_20/20260718_20_combined_detail_p02_4x3_grid.png",
                  "full_bytes": 733140
                },
                {
                  "id": "detail_p03",
                  "lead": 48,
                  "lead_label": "07-20 08-20",
                  "valid_label": "",
                  "file": "https://iaplacs-forecast-images-hk.oss-cn-hongkong.aliyuncs.com/iaplacs/data/current/maps/wrf_montage_20260718_20/20260718_20_combined_detail_p03_4x3_grid.webp",
                  "bytes": 1114307,
                  "preview_file": "https://iaplacs-forecast-images-hk.oss-cn-hongkong.aliyuncs.com/iaplacs/data/current/maps/wrf_montage_20260718_20/20260718_20_combined_detail_p03_4x3_grid.preview.webp",
                  "preview_bytes": 331894,
                  "full_file": "https://iaplacs-forecast-images-hk.oss-cn-hongkong.aliyuncs.com/iaplacs/data/current/maps/wrf_montage_20260718_20/20260718_20_combined_detail_p03_4x3_grid.png",
                  "full_bytes": 720492
                }
              ]
            }
          ]
        }
      ]
    }
  }
}
